hyperstyle/__init__.py
hyperstyle/src/__init__.py
hyperstyle/src/python/__init__.py
hyperstyle/src/python/common/__init__.py
hyperstyle/src/python/common/tool_arguments.py
hyperstyle/src/python/review/__init__.py
hyperstyle/src/python/review/application_config.py
hyperstyle/src/python/review/logging_config.py
hyperstyle/src/python/review/run_tool.py
hyperstyle/src/python/review/common/__init__.py
hyperstyle/src/python/review/common/file_system.py
hyperstyle/src/python/review/common/java_compiler.py
hyperstyle/src/python/review/common/language.py
hyperstyle/src/python/review/common/parallel_runner.py
hyperstyle/src/python/review/common/subprocess_runner.py
hyperstyle/src/python/review/inspectors/__init__.py
hyperstyle/src/python/review/inspectors/base_inspector.py
hyperstyle/src/python/review/inspectors/inspector_type.py
hyperstyle/src/python/review/inspectors/issue.py
hyperstyle/src/python/review/inspectors/issue_configs.py
hyperstyle/src/python/review/inspectors/checkstyle/__init__.py
hyperstyle/src/python/review/inspectors/checkstyle/checkstyle.py
hyperstyle/src/python/review/inspectors/checkstyle/issue_configs.py
hyperstyle/src/python/review/inspectors/checkstyle/issue_types.py
hyperstyle/src/python/review/inspectors/checkstyle/files/config.xml
hyperstyle/src/python/review/inspectors/common/__init__.py
hyperstyle/src/python/review/inspectors/common/base_issue_converter.py
hyperstyle/src/python/review/inspectors/common/tips.py
hyperstyle/src/python/review/inspectors/common/utils.py
hyperstyle/src/python/review/inspectors/common/xml_parser.py
hyperstyle/src/python/review/inspectors/detekt/__init__.py
hyperstyle/src/python/review/inspectors/detekt/detekt.py
hyperstyle/src/python/review/inspectors/detekt/issue_configs.py
hyperstyle/src/python/review/inspectors/detekt/issue_types.py
hyperstyle/src/python/review/inspectors/detekt/files/detekt-config.yml
hyperstyle/src/python/review/inspectors/eslint/.eslintrc
hyperstyle/src/python/review/inspectors/eslint/__init__.py
hyperstyle-1.4.2.dist-info/LICENSE
hyperstyle-1.4.2.dist-info/METADATA
hyperstyle-1.4.2.dist-info/WHEEL
hyperstyle-1.4.2.dist-info/entry_points.txt
hyperstyle-1.4.2.dist-info/top_level.txt
hyperstyle-1.4.2.dist-info/RECORD
