Metadata-Version: 2.1
Name: hyperstyle
Version: 1.4.2
Summary: A tool for running a set of pre-configured linters and evaluating code quality.
Home-page: https://github.com/hyperskill/hyperstyle
Author: Stepik.org
Author-email: ivan.magda@stepik.org
Keywords: code review
Classifier: Development Status :: 3 - Alpha
Classifier: Intended Audience :: Developers
Classifier: Topic :: Software Development :: Build Tools
Classifier: License :: OSI Approved :: MIT License
Classifier: Programming Language :: Python :: 3
Classifier: Operating System :: OS Independent
Requires-Python: >=3.8, <4
License-File: LICENSE
Requires-Dist: setuptools (==56.0.0)
Requires-Dist: pylint (==2.7.4)
Requires-Dist: pylint-django (==2.3.0)
Requires-Dist: flake8 (==3.9.0)
Requires-Dist: flake8-plugin-utils (==1.3.2)
Requires-Dist: flake8-bugbear (==21.4.3)
Requires-Dist: flake8-builtins (==1.5.3)
Requires-Dist: flake8-comprehensions (==3.4.0)
Requires-Dist: flake8-eradicate (==1.0.0)
Requires-Dist: flake8-import-order (==0.18.1)
Requires-Dist: flake8-polyfill (==1.0.2)
Requires-Dist: flake8-return (==1.1.2)
Requires-Dist: flake8-spellcheck (==0.24.0)
Requires-Dist: mccabe (==0.6.1)
Requires-Dist: pep8-naming (==0.11.1)
Requires-Dist: wps-light (==0.15.2)
Requires-Dist: flake8-broken-line (==0.3.0)
Requires-Dist: flake8-string-format (==0.3.0)
Requires-Dist: flake8-commas (==2.0.0)
Requires-Dist: cohesion (==1.0.0)
Requires-Dist: radon (==4.5.0)
Requires-Dist: django (==3.2)
Requires-Dist: requests (==2.25.1)
Requires-Dist: argparse (==1.4.0)
